waqi_client_async/__init__.py
waqi_client_async-1.0.0.dist-info/LICENSE
waqi_client_async-1.0.0.dist-info/WHEEL
waqi_client_async-1.0.0.dist-info/METADATA
waqi_client_async-1.0.0.dist-info/RECORD
